irbasis3/__init__.py
irbasis3/_roots.py
irbasis3/adapter.py
irbasis3/augmentation.py
irbasis3/basis.py
irbasis3/composite.py
irbasis3/gauss.py
irbasis3/kernel.py
irbasis3/poly.py
irbasis3/sampling.py
irbasis3/svd.py
irbasis3/sve.py
irbasis3-3.0a8.dist-info/LICENSE.txt
irbasis3-3.0a8.dist-info/METADATA
irbasis3-3.0a8.dist-info/WHEEL
irbasis3-3.0a8.dist-info/top_level.txt
irbasis3-3.0a8.dist-info/RECORD
