Metadata-Version: 2.1
Name: irbasis3
Version: 3.0a8
Summary: intermediate representation (IR) basis for electronic propagator
Home-page: https://github.com/SpM-lab/irbasis3
Author: ['Markus Wallerberger', 'Hiroshi Shinaoka', 'Kazuyoshi Yoshimi', 'Junya Otsuki', 'Chikano Naoya']
Author-email: markus.wallerberger@tuwien.ac.at
License: UNKNOWN
Keywords: irbasis
Platform: UNKNOWN
Classifier: Development Status :: 3 - Alpha
Classifier: Intended Audience :: Developers
Classifier: Intended Audience :: Science/Research
Classifier: Topic :: Scientific/Engineering :: Physics
Classifier: License :: OSI Approved :: MIT License
Classifier: Programming Language :: Python :: 3
Requires-Python: >=3
License-File: LICENSE.txt
Requires-Dist: numpy
Requires-Dist: scipy
Requires-Dist: setuptools
Provides-Extra: doc
Requires-Dist: sphinx (>=2.1) ; extra == 'doc'
Requires-Dist: myst-parser ; extra == 'doc'
Requires-Dist: sphinx-rtd-theme ; extra == 'doc'
Provides-Extra: test
Requires-Dist: pytest ; extra == 'test'
Requires-Dist: irbasis ; extra == 'test'
Requires-Dist: xprec ; extra == 'test'
Provides-Extra: xprec
Requires-Dist: xprec (>=1.1.1) ; extra == 'xprec'
